hs2client/__init__.py
hs2client/commons.py
hs2client/hs2client.py
hs2client/genthrift/__init__.py
hs2client/genthrift/TCLIService/TCLIService.py
hs2client/genthrift/TCLIService/__init__.py
hs2client/genthrift/TCLIService/constants.py
hs2client/genthrift/TCLIService/ttypes.py
hs2client-0.1.1.dist-info/METADATA
hs2client-0.1.1.dist-info/RECORD
hs2client-0.1.1.dist-info/WHEEL
hs2client-0.1.1.dist-info/top_level.txt
