Metadata-Version: 2.1
Name: hs2client
Version: 0.1.1
Summary: A package interact with Hive Server 2 via the Thrift protocol
Home-page: https://github.com/gglanzani/hs2client
Author: Giovanni Lanzani
Author-email: giovanni@lanzani.nl
License: Apache 2.0
Keywords: hive data database thrift metastore
Platform: UNKNOWN
Classifier: Development Status :: 4 - Beta
Classifier: Intended Audience :: Information Technology
Classifier: Topic :: Database
Classifier: License :: OSI Approved :: Apache Software License
Classifier: Programming Language :: Python :: 3
Classifier: Programming Language :: Python :: 3.5
Classifier: Programming Language :: Python :: 3.6
Provides-Extra: dev
Provides-Extra: test
Requires-Dist: thrift
Requires-Dist: click
Requires-Dist: future
Requires-Dist: thrift-sasl
Provides-Extra: dev
Requires-Dist: pytest; extra == 'dev'
Provides-Extra: test
Requires-Dist: pytest; extra == 'test'
